commons/__init__.py
commons/logger.py
detect/Detection.py
detect/__init__.py
detect/categorical.py
detect/getType.py
detect/loader.py
detect/stats.py
detect/testDetection.py
label/SimilarityMeasures.py
label/__init__.py
label/categorical.py
label/classification.py
label/cmd.py
label/features.py
label/loader.py
label/model_construction.py
ttla/commons/__init__.py
ttla/commons/logger.py
ttla/detect/Detection.py
ttla/detect/__init__.py
ttla/detect/categorical.py
ttla/detect/getType.py
ttla/detect/loader.py
ttla/detect/stats.py
ttla/detect/testDetection.py
ttla/label/SimilarityMeasures.py
ttla/label/__init__.py
ttla/label/categorical.py
ttla/label/classification.py
ttla/label/cmd.py
ttla/label/features.py
ttla/label/loader.py
ttla/label/model_construction.py
ttla-1.0.4.dist-info/LICENSE
ttla-1.0.4.dist-info/METADATA
ttla-1.0.4.dist-info/WHEEL
ttla-1.0.4.dist-info/top_level.txt
ttla-1.0.4.dist-info/RECORD
