Metadata-Version: 2.1
Name: ttla
Version: 1.0.4
Summary: Typology-based semantic labelling of numeric columns
Home-page: https://github.com/oeg-upm/ttla
Author: Ahmad Alobaid, Emilia Kacprzak
Author-email: aalobaid@fi.upm.es
Classifier: Programming Language :: Python :: 3
Classifier: License :: OSI Approved :: Apache Software License
Classifier: Operating System :: OS Independent
Requires-Python: >=3.6
License-File: LICENSE
Requires-Dist: easysparql
Requires-Dist: Flask
Requires-Dist: requests
Requires-Dist: rdflib
Requires-Dist: PPool
Requires-Dist: pandas
Requires-Dist: fuzzycmeans
Requires-Dist: coverage
Requires-Dist: chardet
